arknights_toolkit-0.7.10.dist-info/METADATA
arknights_toolkit-0.7.10.dist-info/WHEEL
arknights_toolkit-0.7.10.dist-info/entry_points.txt
arknights_toolkit-0.7.10.dist-info/licenses/LICENSE
arknights_toolkit/__init__.py
arknights_toolkit/cli/__init__.py
arknights_toolkit/cli/__main__.py
arknights_toolkit/cli/plugins/__init__.py
arknights_toolkit/cli/plugins/clear.py
arknights_toolkit/cli/plugins/init.py
arknights_toolkit/cli/plugins/update.py
arknights_toolkit/gacha/__init__.py
arknights_toolkit/gacha/main.py
arknights_toolkit/gacha/model.py
arknights_toolkit/gacha/simulate.py
arknights_toolkit/images.py
arknights_toolkit/random_operator.py
arknights_toolkit/record/__init__.py
arknights_toolkit/record/database.py
arknights_toolkit/record/drawer.py
arknights_toolkit/record/main.py
arknights_toolkit/record/style.py
arknights_toolkit/recruit.py
arknights_toolkit/resource/HarmonyOS_Sans_SC_Medium.ttf
arknights_toolkit/resource/example_recruiment.json
arknights_toolkit/resource/gacha/back_five.png
arknights_toolkit/resource/gacha/back_four.png
arknights_toolkit/resource/gacha/back_image.png
arknights_toolkit/resource/gacha/back_six.png
arknights_toolkit/resource/gacha/five.png
arknights_toolkit/resource/gacha/four.png
arknights_toolkit/resource/gacha/rarity_table.json
arknights_toolkit/resource/gacha/six_01.png
arknights_toolkit/resource/gacha/six_02.png
arknights_toolkit/resource/gacha/star_02.png
arknights_toolkit/resource/gacha/半身像_无_1.png
arknights_toolkit/resource/gacha/图标_职业_先锋_大图_白.png
arknights_toolkit/resource/gacha/图标_职业_医疗_大图_白.png
arknights_toolkit/resource/gacha/图标_职业_术师_大图_白.png
arknights_toolkit/resource/gacha/图标_职业_特种_大图_白.png
arknights_toolkit/resource/gacha/图标_职业_狙击_大图_白.png
arknights_toolkit/resource/gacha/图标_职业_辅助_大图_白.png
arknights_toolkit/resource/gacha/图标_职业_近卫_大图_白.png
arknights_toolkit/resource/gacha/图标_职业_重装_大图_白.png
arknights_toolkit/resource/gacha/稀有度_白_2.png
arknights_toolkit/resource/gacha/稀有度_白_3.png
arknights_toolkit/resource/gacha/稀有度_白_4.png
arknights_toolkit/resource/gacha/稀有度_白_5.png
arknights_toolkit/resource/operator_template.json
arknights_toolkit/resource/record/arkgacha_record.db
arknights_toolkit-0.7.10.dist-info/RECORD
