Metadata-Version: 2.1
Name: arknights-toolkit
Version: 0.7.10
Summary: Arknights-related Toolkit
Author-Email: RF-Tar-Railt <rf_tar_railt@qq.com>
License: AGPL-3.0
Project-URL: repository, https://github.com/RF-Tar-Railt/arknights-toolkit
Requires-Python: >=3.9
Requires-Dist: Pillow>=10.2.0
Requires-Dist: httpx<1.0.0,>=0.26.0
Requires-Dist: loguru>=0.7.2
Requires-Dist: lxml>=5.1.0
Requires-Dist: matplotlib>=3.7.5
Requires-Dist: cli-lite>=0.10.0
Requires-Dist: msgpack>=1.0.8
Requires-Dist: ujson>=5.9.0
